pygame_texteditor/__init__.py
pygame_texteditor/_caret.py
pygame_texteditor/_customization.py
pygame_texteditor/_editor_getters.py
pygame_texteditor/_input_handling_keyboard.py
pygame_texteditor/_input_handling_keyboard_highlight.py
pygame_texteditor/_input_handling_mouse.py
pygame_texteditor/_letter_operations.py
pygame_texteditor/_other.py
pygame_texteditor/_rendering.py
pygame_texteditor/_rendering_highlighting.py
pygame_texteditor/_rendering_syntax_coloring.py
pygame_texteditor/_scrollbar_vertical.py
pygame_texteditor/_usage.py
pygame_texteditor/ColorFormatter.py
pygame_texteditor/elements/colorstyles/bright.yml
pygame_texteditor/elements/colorstyles/dark.yml
pygame_texteditor/elements/fonts/Courier.ttf
pygame_texteditor/elements/graphics/Scroll_Bar.png
pygame_texteditor/TextEditor.py
pygame_texteditor-0.7.3.dist-info/LICENSE
pygame_texteditor-0.7.3.dist-info/METADATA
pygame_texteditor-0.7.3.dist-info/WHEEL
pygame_texteditor-0.7.3.dist-info/RECORD
