Metadata-Version: 2.1
Name: pygame-texteditor
Version: 0.7.3
Summary: A WYSIWYG-texteditor based on pygame.
License: MIT
Keywords: pygame,texteditor,text,editor
Author: Victor Seifert
Author-email: seifert.victor@web.de
Requires-Python: >=3.8,<4.0
Classifier: Development Status :: 5 - Production/Stable
Classifier: Intended Audience :: Developers
Classifier: License :: OSI Approved :: MIT License
Classifier: Natural Language :: English
Classifier: Programming Language :: Python
Classifier: Programming Language :: Python :: 3
Classifier: Programming Language :: Python :: 3.8
Classifier: Programming Language :: Python :: 3.9
Classifier: Programming Language :: Python :: 3.10
Classifier: Programming Language :: Python :: 3.11
Classifier: Programming Language :: Python :: 3.6
Classifier: Topic :: Software Development
Classifier: Topic :: Software Development :: Libraries
Classifier: Topic :: Software Development :: Libraries :: Python Modules
Requires-Dist: PyYAML (>=5.3.1)
Requires-Dist: Pygments (>=2.6.1)
Requires-Dist: pygame (>=1.9.6)
Requires-Dist: pyperclip (>=1.8.1)
